{
    "ProjectsInfoList": [
        {
            "id": 1,
            "name": "Adalab Landing Page",
            "created": {
                "year": 2020,
                "month": 2
            },
            "status": "finished",
            "type": "proyecto individual realizado en Adalab",
            "description": "Proyecto realizado como alumna de Adalab para la evaluación intermedia del Módulo 1. Landing page para el portal de Adalab realizado con HTML y CSS.",
            "imageURL": "https://repository-images.githubusercontent.com/247160544/fa5ac680-8fbf-11ea-9d37-93735cb04e8e",
            "codeURL": "https://github.com/beatriz-perez/modulo-1-evaluacion-intermedia-beatriz-perez",
            "demoURL": "https://beatriz-perez.github.io/modulo-1-evaluacion-intermedia-beatriz-perez/"
        },
        {
            "id": 2,
            "name": "Anonymous Proxy",
            "created": {
                "year": 2020,
                "month": 2
            },
            "status": "finished",
            "type": "proyecto individual realizado en Adalab",
            "description": "Proyecto realizado como alumna de Adalab para la evaluación final del Módulo 1. Website promocional realizado con HTML y SASS.",
            "imageURL": "https://repository-images.githubusercontent.com/247160626/d21f9780-8fc0-11ea-9b99-f18d51445bce",
            "codeURL": "https://github.com/beatriz-perez/modulo-1-evaluacion-final-beatriz-perez",
            "demoURL": "https://beatriz-perez.github.io/modulo-1-evaluacion-final-beatriz-perez/"
        },
        {
            "id": 3,
            "name": "What A Puzzle",
            "created": {
                "year": 2020,
                "month": 2
            },
            "status": "finished",
            "type": "proyecto de grupo realizado en Adalab",
            "description": "Proyecto grupal realizado como alumna de Adalab durante el Módulo 1. Website de presentación de equipo realizado con HTML y SASS aplicando metodologías de trabajo colaborativo.",
            "imageURL": "https://repository-images.githubusercontent.com/247159921/fc258980-8fc1-11ea-8063-0dc399b40530",
            "codeURL": "https://github.com/beatriz-perez/project-promo-i-module-1-team-2-afternoon",
            "demoURL": "https://beatriz-perez.github.io/project-promo-i-module-1-team-2-afternoon/"
        },
        {
            "id": 4,
            "name": "Spells",
            "created": {
                "year": 2020,
                "month": 3
            },
            "status": "ongoing",
            "type": "proyecto personal",
            "description": "Proyecto personal realizado como práctica de maquetación. Web realizada con HTML y CSS en la que se recopilan métodos y trucos.",
            "imageURL": "https://repository-images.githubusercontent.com/246540742/56e06600-95fe-11ea-824a-1ae79efb846a",
            "codeURL": "https://github.com/beatriz-perez/spells",
            "demoURL": "https://beatriz-perez.github.io/spells/"
        },
        {
            "id": 5,
            "name": "Adivina el número",
            "created": {
                "year": 2020,
                "month": 3
            },
            "status": "finished",
            "type": "proyecto individual realizado en Adalab",
            "description": "Proyecto realizado como alumna de Adalab para la evaluación intermedia del Módulo 2. Juego que consiste en adivinar un número aleatorio guiándonos por las pistas que nos devuelve el programa con cada intento. Realizado con HTML, CSS y JavaScript.",
            "imageURL": "https://repository-images.githubusercontent.com/247160723/8ec62880-8fc2-11ea-89f6-1bfede92b405",
            "codeURL": "https://github.com/beatriz-perez/modulo-2-evaluacion-intermedia-beatriz-perez",
            "demoURL": "https://beatriz-perez.github.io/modulo-2-evaluacion-intermedia-beatriz-perez/"
        },
        {
            "id": 6,
            "name": "Show Finder",
            "created": {
                "year": 2020,
                "month": 3
            },
            "status": "finished",
            "type": "proyecto individual realizado en Adalab",
            "description": "Proyecto realizado como alumna de Adalab para la evaluación final del Módulo 2. Web de búsqueda de series que nos permite guardar nuestras favoritas y consultar información de cada una de ellas, así como acceder a sus websites oficiales. Realizado con HTML, SASS y JavaScript.",
            "imageURL": "https://repository-images.githubusercontent.com/249420474/a66eb900-79e4-11ea-8329-900e4b53b9e2",
            "codeURL": "https://github.com/beatriz-perez/modulo-2-evaluacion-final-beatriz-perez",
            "demoURL": "https://beatriz-perez.github.io/modulo-2-evaluacion-final-beatriz-perez/"
        },
        {
            "id": 7,
            "name": "Awesome Profile Cards",
            "created": {
                "year": 2020,
                "month": 2
            },
            "status": "finished",
            "type": "proyecto de grupo realizado en Adalab",
            "description": "Proyecto grupal realizado como alumna de Adalab durante el Módulo 2. Website de creación de tarjetas de presentación compartibles realizado con HTML, SASS y JavasCript aplicando marcos de trabajo colaborativo y Agile.",
            "imageURL": "https://repository-images.githubusercontent.com/250485444/4a875800-8fc3-11ea-86c3-77e8da8722bd",
            "codeURL": "https://github.com/beatriz-perez/project-promo-i-module-2-team-4-afternoon",
            "demoURL": "https://beatriz-perez.github.io/project-promo-i-module-2-team-4-afternoon/"
        },
        {
            "id": 8,
            "name": "Ask The Ball",
            "created": {
                "year": 2020,
                "month": 3
            },
            "status": "finished",
            "type": "proyecto personal",
            "description": "Aplicación web realizada al comienzo de la Crisis del Coronavirus en la que el usuario puede realizar preguntas acerca del futuro que serán respondidas por la bola 8 mágica. Realizada empleando HTML, CSS y JavasCript.",
            "imageURL": "https://repository-images.githubusercontent.com/247236546/dc9b6180-660d-11ea-86c7-e9fe77fb0e44",
            "codeURL": "https://github.com/beatriz-perez/Ask-The-Ball",
            "demoURL": "https://beatriz-perez.github.io/Ask-The-Ball/"
        },
        {
            "id": 9,
            "name": "Mi Lista de Pokemon",
            "created": {
                "year": 2020,
                "month": 4
            },
            "status": "finished",
            "type": "proyecto individual realizado en Adalab",
            "description": "Proyecto realizado como alumna de Adalab para la evaluación intermedia del Módulo 3. Web desarrollada con React que consiste en un listado de pokemon con una tarjeta para cada uno con información relevante, como el nombre, tipos y una imagen.",
            "imageURL": "https://repository-images.githubusercontent.com/253772228/735c1d00-8fc4-11ea-8c8a-25205760ca78",
            "codeURL": "https://github.com/beatriz-perez/modulo-3-evaluacion-intermedia-beatriz-perez",
            "demoURL": "https://beatriz-perez.github.io/modulo-3-evaluacion-intermedia-beatriz-perez/"
        },
        {
            "id": 10,
            "name": "Rick & Morty Cards",
            "created": {
                "year": 2020,
                "month": 4
            },
            "status": "finished",
            "type": "proyecto individual realizado en Adalab",
            "description": "Proyecto realizado como alumna de Adalab para la evaluación final del Módulo 3. Página web con un listado de personajes de Rick and Morty, que podemos filtrar por nombre, especie, estado... Desarrollado empleando React y SASS.",
            "imageURL": "https://repository-images.githubusercontent.com/261122647/2af12f00-8fc5-11ea-87c0-b7f0ad5571b0",
            "codeURL": "https://github.com/beatriz-perez/modulo-3-evaluacion-final-beatriz-perez",
            "demoURL": "https://beatriz-perez.github.io/modulo-3-evaluacion-final-beatriz-perez/"
        },
        {
            "id": 11,
            "name": "React Profile Cards",
            "created": {
                "year": 2020,
                "month": 4
            },
            "status": "finished",
            "type": "proyecto de grupo realizado en Adalab",
            "description": "Proyecto grupal de refactorización de código heredado realizado como alumna de Adalab durante el Módulo 3. Website de creación de tarjetas de presentación compartibles realizado con React y SASS aplicando marcos de trabajo colaborativo y Agile.",
            "imageURL": "https://repository-images.githubusercontent.com/261124558/8839b000-8fc6-11ea-8932-54b729bac6ad",
            "codeURL": "https://github.com/beatriz-perez/project-promo-i-module-3-team-1-afternoon-beatriz-perez",
            "demoURL": "https://beatriz-perez.github.io/project-promo-i-module-3-team-1-afternoon-beatriz-perez/"
        },
        {
            "id": 12,
            "name": "My Project Index",
            "created": {
                "year": 2020,
                "month": 3
            },
            "status": "ongoing",
            "type": "proyecto personal",
            "description": "Portfolio online desarrollado con React y Sass para la presentación y exposición ordenada de los royectos realizados por Beatriz Pérez como FrontEnd Devaloper.",
            "imageURL": "https://repository-images.githubusercontent.com/263891662/31def980-95e4-11ea-9693-fa16a0693d82",
            "codeURL": "https://github.com/beatriz-perez/Index",
            "demoURL": "https://beatriz-perez.github.io/Index/"
        },
        {
            "id": 13,
            "name": "Check My Repos",
            "created": {
                "year": 2020,
                "month": 4
            },
            "status": "ongoing",
            "type": "proyecto personal",
            "description": "Aplicación web de búsqueda y realización de listados de usuarios y repositorios de GitHub según criterios a definir por el usuario. Desarrollada con React.",
            "imageURL": "https://repository-images.githubusercontent.com/255313584/6ad79800-95fd-11ea-80e2-0b5e23b8e77f",
            "codeURL": "https://github.com/beatriz-perez/check-my-repos",
            "demoURL": "https://beatriz-perez.github.io/check-my-repos/"
        }
    ]
}